setup.py
bufferapp_logger.egg-info/PKG-INFO
bufferapp_logger.egg-info/SOURCES.txt
bufferapp_logger.egg-info/dependency_links.txt
bufferapp_logger.egg-info/not-zip-safe
bufferapp_logger.egg-info/requires.txt
bufferapp_logger.egg-info/top_level.txt
logger/__init__.py
logger/logger.py