Metadata-Version: 1.1
Name: bufferapp-logger
Version: 0.0.5
Summary: Python Logger library for Bufferapp.
Home-page: https://github.com/bufferapp/python-logger
Author: Steven Cheng
Author-email: stevenc81@gmail.com
License: MIT
Download-URL: https://github.com/bufferapp/python-logger/archive/master.zip
Platform: any
